{"name":"Inicios de sesion Fallido  \u003ctestCase\u003e","id":"inicio-de-sesion-pagina-newtours;inicios-de-sesion-fallido--\u003ctestcase\u003e","testSteps":[{"number":1,"description":"Example: {Usuario\u003dicer13, Clave\u003da1234}","duration":9269,"startTime":"2020-05-18T07:54:38.160-05:00[America/Bogota]","screenshots":[{"screenshot":"03a8f1afddb6294d8b0ef1f8e56e151f38f502c61d29291e750c775bdbd47b0a.png","timeStamp":1589806487429}],"result":"SUCCESS","precondition":false,"level":0,"children":[{"number":2,"description":"Dado que estoy en la pagina de inicio de NewTours","duration":5745,"startTime":"2020-05-18T07:54:38.165-05:00[America/Bogota]","screenshots":[{"screenshot":"a53496269f57fd885e9e9f74dd20f892423bd77975914e66bf914834bf38b3da.png","timeStamp":1589806483910}],"result":"SUCCESS","precondition":false,"level":1,"children":[{"number":3,"description":"Abrir aplicacion new tours","duration":5737,"startTime":"2020-05-18T07:54:38.171-05:00[America/Bogota]","screenshots":[{"screenshot":"a53496269f57fd885e9e9f74dd20f892423bd77975914e66bf914834bf38b3da.png","timeStamp":1589806483908}],"result":"SUCCESS","precondition":false,"level":2}]},{"number":4,"description":"Cuando ingreso mis credenciales\r\n| usuario | clave |\r\n| icer13 | a1234 |","duration":3184,"startTime":"2020-05-18T07:54:43.911-05:00[America/Bogota]","screenshots":[{"screenshot":"a53496269f57fd885e9e9f74dd20f892423bd77975914e66bf914834bf38b3da.png","timeStamp":1589806483912},{"screenshot":"03a8f1afddb6294d8b0ef1f8e56e151f38f502c61d29291e750c775bdbd47b0a.png","timeStamp":1589806487095}],"result":"SUCCESS","precondition":false,"level":1,"children":[{"number":5,"description":"Escribir usuario: icer13","duration":475,"startTime":"2020-05-18T07:54:43.914-05:00[America/Bogota]","screenshots":[{"screenshot":"a53496269f57fd885e9e9f74dd20f892423bd77975914e66bf914834bf38b3da.png","timeStamp":1589806483916},{"screenshot":"20b5835e196f43b15bb981d1811efdccf346ce99f2e74af669c5ed36e434e41d.png","timeStamp":1589806484389}],"result":"SUCCESS","precondition":false,"level":2},{"number":6,"description":"Escribir clave: a1234","duration":443,"startTime":"2020-05-18T07:54:44.390-05:00[America/Bogota]","screenshots":[{"screenshot":"20b5835e196f43b15bb981d1811efdccf346ce99f2e74af669c5ed36e434e41d.png","timeStamp":1589806484392},{"screenshot":"6ad03109648fd4861c22ed1d50654e5f80da4fabc67dbcec7e32830b8223b26a.png","timeStamp":1589806484833}],"result":"SUCCESS","precondition":false,"level":2},{"number":7,"description":"Aqui hice click en login","duration":2259,"startTime":"2020-05-18T07:54:44.834-05:00[America/Bogota]","screenshots":[{"screenshot":"6ad03109648fd4861c22ed1d50654e5f80da4fabc67dbcec7e32830b8223b26a.png","timeStamp":1589806484836},{"screenshot":"03a8f1afddb6294d8b0ef1f8e56e151f38f502c61d29291e750c775bdbd47b0a.png","timeStamp":1589806487093}],"result":"SUCCESS","precondition":false,"level":2}]},{"number":8,"description":"Entonces valido el error de ingreso","duration":46,"startTime":"2020-05-18T07:54:47.096-05:00[America/Bogota]","screenshots":[{"screenshot":"03a8f1afddb6294d8b0ef1f8e56e151f38f502c61d29291e750c775bdbd47b0a.png","timeStamp":1589806487097},{"screenshot":"03a8f1afddb6294d8b0ef1f8e56e151f38f502c61d29291e750c775bdbd47b0a.png","timeStamp":1589806487142}],"result":"SUCCESS","precondition":false,"level":1,"children":[{"number":9,"description":"Se revisa el SIGN-ON","duration":42,"startTime":"2020-05-18T07:54:47.098-05:00[America/Bogota]","screenshots":[{"screenshot":"03a8f1afddb6294d8b0ef1f8e56e151f38f502c61d29291e750c775bdbd47b0a.png","timeStamp":1589806487100},{"screenshot":"03a8f1afddb6294d8b0ef1f8e56e151f38f502c61d29291e750c775bdbd47b0a.png","timeStamp":1589806487140}],"result":"SUCCESS","precondition":false,"level":2}]}]},{"number":10,"description":"Example: {Usuario\u003dicer14, Clave\u003dadmin}","duration":8968,"startTime":"2020-05-18T07:54:48.179-05:00[America/Bogota]","screenshots":[{"screenshot":"03a8f1afddb6294d8b0ef1f8e56e151f38f502c61d29291e750c775bdbd47b0a.png","timeStamp":1589806497147}],"result":"SUCCESS","precondition":false,"level":0,"children":[{"number":11,"description":"Dado que estoy en la pagina de inicio de NewTours","duration":5529,"startTime":"2020-05-18T07:54:48.182-05:00[America/Bogota]","screenshots":[{"screenshot":"a53496269f57fd885e9e9f74dd20f892423bd77975914e66bf914834bf38b3da.png","timeStamp":1589806493711}],"result":"SUCCESS","precondition":false,"level":1,"children":[{"number":12,"description":"Abrir aplicacion new tours","duration":5517,"startTime":"2020-05-18T07:54:48.192-05:00[America/Bogota]","screenshots":[{"screenshot":"a53496269f57fd885e9e9f74dd20f892423bd77975914e66bf914834bf38b3da.png","timeStamp":1589806493709}],"result":"SUCCESS","precondition":false,"level":2}]},{"number":13,"description":"Cuando ingreso mis credenciales\r\n| usuario | clave |\r\n| icer14 | admin |","duration":3091,"startTime":"2020-05-18T07:54:53.713-05:00[America/Bogota]","screenshots":[{"screenshot":"a53496269f57fd885e9e9f74dd20f892423bd77975914e66bf914834bf38b3da.png","timeStamp":1589806493715},{"screenshot":"03a8f1afddb6294d8b0ef1f8e56e151f38f502c61d29291e750c775bdbd47b0a.png","timeStamp":1589806496804}],"result":"SUCCESS","precondition":false,"level":1,"children":[{"number":14,"description":"Escribir usuario: icer14","duration":445,"startTime":"2020-05-18T07:54:53.716-05:00[America/Bogota]","screenshots":[{"screenshot":"a53496269f57fd885e9e9f74dd20f892423bd77975914e66bf914834bf38b3da.png","timeStamp":1589806493717},{"screenshot":"49562d4705df23bedee67e72678439cf3f0c42a483612d23b69d9c3fe58623c3.png","timeStamp":1589806494160}],"result":"SUCCESS","precondition":false,"level":2},{"number":15,"description":"Escribir clave: admin","duration":413,"startTime":"2020-05-18T07:54:54.162-05:00[America/Bogota]","screenshots":[{"screenshot":"49562d4705df23bedee67e72678439cf3f0c42a483612d23b69d9c3fe58623c3.png","timeStamp":1589806494165},{"screenshot":"3a1f42a1547b92066994a1bd8a24f80b736c0fe61d140830643bb75a24455004.png","timeStamp":1589806494575}],"result":"SUCCESS","precondition":false,"level":2},{"number":16,"description":"Aqui hice click en login","duration":2226,"startTime":"2020-05-18T07:54:54.576-05:00[America/Bogota]","screenshots":[{"screenshot":"3a1f42a1547b92066994a1bd8a24f80b736c0fe61d140830643bb75a24455004.png","timeStamp":1589806494579},{"screenshot":"03a8f1afddb6294d8b0ef1f8e56e151f38f502c61d29291e750c775bdbd47b0a.png","timeStamp":1589806496802}],"result":"SUCCESS","precondition":false,"level":2}]},{"number":17,"description":"Entonces valido el error de ingreso","duration":339,"startTime":"2020-05-18T07:54:56.805-05:00[America/Bogota]","screenshots":[{"screenshot":"03a8f1afddb6294d8b0ef1f8e56e151f38f502c61d29291e750c775bdbd47b0a.png","timeStamp":1589806497144}],"result":"SUCCESS","precondition":false,"level":1,"children":[{"number":18,"description":"Se revisa el SIGN-ON","duration":333,"startTime":"2020-05-18T07:54:56.807-05:00[America/Bogota]","screenshots":[{"screenshot":"03a8f1afddb6294d8b0ef1f8e56e151f38f502c61d29291e750c775bdbd47b0a.png","timeStamp":1589806497140}],"result":"SUCCESS","precondition":false,"level":2}]}]}],"userStory":{"id":"inicio-de-sesion-pagina-newtours","storyName":"Inicio de Sesion pagina NewTours","path":"src/test/resources/com/newtours/testing/features/login.feature","type":"feature"},"featureTag":{"name":"Features/Inicio de Sesion pagina NewTours","type":"feature","displayName":"Features/Inicio de Sesion pagina NewTours"},"title":"Inicios de sesion Fallido  \u003ctestCase\u003e","tags":[{"name":"Fallido","type":"tag","displayName":"Fallido"}],"startTime":"2020-05-18T07:54:38.145-05:00[America/Bogota]","duration":19765,"projectKey":"","isManualTestingUpToDate":false,"dataTable":{"headers":["Usuario","Clave"],"rows":[{"values":["icer13","a1234"],"result":"SUCCESS"},{"values":["icer14","admin"],"result":"SUCCESS"}],"predefinedRows":true,"scenarioOutline":"Dado que estoy en la pagina de inicio de NewTours\n\rCuando ingreso mis credenciales\n\rEntonces valido el error de ingreso\n\r","dataSetDescriptors":[{"startRow":0,"rowCount":0,"name":""}]},"manual":false,"testSource":"Cucumber","result":"SUCCESS","scenarioOutline":"Dado que estoy en la pagina de inicio de NewTours\r\nCuando ingreso mis credenciales\r\n|usuario | clave|\r\n|\u003cUsuario\u003e | \u003cClave\u003e|\r\nEntonces valido el error de ingreso"}